nycto_annotator/__init__.py
nycto_annotator/nycto_annotator.py
nycto_annotator/create_bbox/__init__.py
nycto_annotator/create_bbox/bbox.py
nycto_annotator/grounding_dino/__init__.py
nycto_annotator/grounding_dino/run.py
nycto_annotator-0.1.5.dist-info/licenses/LICENSE
nycto_annotator-0.1.5.dist-info/METADATA
nycto_annotator-0.1.5.dist-info/WHEEL
nycto_annotator-0.1.5.dist-info/top_level.txt
nycto_annotator-0.1.5.dist-info/RECORD
