Metadata-Version: 2.4
Name: nycto_annotator
Version: 0.1.5
Summary: A simple auto annotator package
Author-email: Niharika <nyctophilicenigma@gmail.com>
License: MIT
Project-URL: Homepage, https://github.com/niharikasingh3632/Python-Package
Requires-Python: >=3.10
License-File: LICENSE
Requires-Dist: torch==2.9.1
Requires-Dist: pillow==12.0.0
Requires-Dist: transformers==4.57.3
Dynamic: license-file
